{
  "lastUpdated": "2026-07-17T07:52:04.696Z",
  "commit": "927b61ab419e98c027c077af81273e73650cb94f",
  "branch": "main",
  "type": "e2e",
  "worlds": {
    "local": {
      "status": "passing",
      "total": 4131,
      "passed": 3631,
      "failed": 0,
      "skipped": 500,
      "frameworks": {
        "astro": {
          "total": 306,
          "passed": 256,
          "failed": 0
        },
        "express": {
          "total": 306,
          "passed": 256,
          "failed": 0
        },
        "fastify": {
          "total": 306,
          "passed": 256,
          "failed": 0
        },
        "hono": {
          "total": 306,
          "passed": 256,
          "failed": 0
        },
        "nextjs-turbopack": {
          "total": 612,
          "passed": 593,
          "failed": 0
        },
        "nextjs-webpack": {
          "total": 459,
          "passed": 440,
          "failed": 0
        },
        "nitro": {
          "total": 306,
          "passed": 256,
          "failed": 0
        },
        "nuxt": {
          "total": 306,
          "passed": 256,
          "failed": 0
        },
        "sveltekit": {
          "total": 306,
          "passed": 294,
          "failed": 0
        },
        "vite": {
          "total": 306,
          "passed": 256,
          "failed": 0
        }
      },
      "progress": 88
    },
    "postgres": {
      "status": "passing",
      "total": 2142,
      "passed": 1873,
      "failed": 0,
      "skipped": 269,
      "frameworks": {
        "astro": {
          "total": 153,
          "passed": 128,
          "failed": 0
        },
        "express": {
          "total": 153,
          "passed": 128,
          "failed": 0
        },
        "fastify": {
          "total": 153,
          "passed": 128,
          "failed": 0
        },
        "hono": {
          "total": 153,
          "passed": 128,
          "failed": 0
        },
        "nextjs-turbopack": {
          "total": 306,
          "passed": 287,
          "failed": 0
        },
        "nextjs-webpack": {
          "total": 306,
          "passed": 287,
          "failed": 0
        },
        "nitro": {
          "total": 153,
          "passed": 128,
          "failed": 0
        },
        "nuxt": {
          "total": 153,
          "passed": 128,
          "failed": 0
        },
        "sveltekit": {
          "total": 153,
          "passed": 147,
          "failed": 0
        },
        "vite": {
          "total": 153,
          "passed": 128,
          "failed": 0
        }
      },
      "progress": 87
    }
  }
}